pyEMIS/__init__.py
pyEMIS/analysis/__init__.py
pyEMIS/analysis/base.py
pyEMIS/analysis/ols_cusum.py
pyEMIS/analysis/profile.py
pyEMIS/data/__init__.py
pyEMIS/data/config.py
pyEMIS/data/dataset.py
pyEMIS/data/datasource.py
pyEMIS/data/panel.py
pyEMIS/data/unit.py
pyEMIS/data/utils.py
pyEMIS/data/adapters/__init__.py
pyEMIS/data/preparation/__init__.py
pyEMIS/data/preparation/cleaners.py
pyEMIS/data/preparation/interpolators.py
pyEMIS/models/__init__.py
pyEMIS/models/any.py
pyEMIS/models/base.py
pyEMIS/models/constant.py
pyEMIS/models/date_format.py
pyEMIS/models/discontinuous.py
pyEMIS/models/heating3.py
pyEMIS/models/weekly.py
pyEMIS-0.9.5.dist-info/METADATA
pyEMIS-0.9.5.dist-info/WHEEL
pyEMIS-0.9.5.dist-info/top_level.txt
pyEMIS-0.9.5.dist-info/RECORD
