Metadata-Version: 2.1
Name: pyEMIS
Version: 0.9.5
Summary: Python library for energy consumption data analysis
Home-page: https://github.com/ggstuart/pyEMIS
Author: Graeme Stuart
Author-email: ggstuart@gmail.com
License: UNKNOWN
Platform: UNKNOWN
Requires-Dist: numpy
Requires-Dist: scipy
Requires-Dist: python-dateutil
